vcrtool/__init__.py
vcrtool/__main__.py
vcrtool/capture_stereo.py
vcrtool/jlip.py
vcrtool/main.py
vcrtool/py.typed
vcrtool/sircs.py
vcrtool/utils.py
vcrtool-0.0.2.dist-info/METADATA
vcrtool-0.0.2.dist-info/WHEEL
vcrtool-0.0.2.dist-info/entry_points.txt
vcrtool-0.0.2.dist-info/licenses/LICENSE.txt
vcrtool-0.0.2.dist-info/RECORD
