Metadata-Version: 2.4
Name: vcrtool
Version: 0.0.2
Summary: Control a JLIP device such as a VCR.
License-Expression: MIT
License-File: LICENSE.txt
Keywords: command line,dvd,jlip,vcr,vhs
Author: Andrew Udvare
Author-email: audvare@gmail.com
Requires-Python: >=3.10,<4.0
Classifier: Development Status :: 4 - Beta
Classifier: Intended Audience :: Developers
Classifier: Programming Language :: Python
Classifier: Programming Language :: Python :: 3.10
Classifier: Programming Language :: Python :: 3.11
Classifier: Programming Language :: Python :: 3.12
Classifier: Programming Language :: Python :: 3.13
Classifier: Programming Language :: Python :: 3.14
Classifier: Typing :: Typed
Requires-Dist: anyio (>=4.12.0,<5.0.0)
Requires-Dist: bascom (>=0.1.0,<0.2.0)
Requires-Dist: click (>=8.3.1,<9.0.0)
Requires-Dist: psutil (>=7.1.3,<8.0.0)
Requires-Dist: pyftdi (>=0.57.1,<0.58.0)
Requires-Dist: pyrate-limiter (>=3.9.0,<4.0.0)
Requires-Dist: pyserial (>=3.5,<4.0)
Requires-Dist: pytimeparse2 (>=1.7.1,<2.0.0)
Requires-Dist: typing-extensions (>=4.15.0,<5.0.0)
Project-URL: Documentation, https://vcrtool.readthedocs.org
Project-URL: Homepage, https://tatsh.github.io/vcrtool/
Project-URL: Issues, https://github.com/Tatsh/vcrtool/issues
Project-URL: Repository, https://github.com/Tatsh/vcrtool
